package_for_testing_gh_actions/__main__.py
package_for_testing_gh_actions-0.1.12.dist-info/licenses/LICENSE
package_for_testing_gh_actions-0.1.12.dist-info/METADATA
package_for_testing_gh_actions-0.1.12.dist-info/WHEEL
package_for_testing_gh_actions-0.1.12.dist-info/entry_points.txt
package_for_testing_gh_actions-0.1.12.dist-info/top_level.txt
package_for_testing_gh_actions-0.1.12.dist-info/RECORD
