Metadata-Version: 2.4
Name: package-for-testing-gh-actions
Version: 0.1.12
Summary: A sample Python project
Author-email: "A. Random Developer" <author@example.com>
Maintainer-email: "A. Great Maintainer" <maintainer@example.com>
License: MIT License
Keywords: sample,setuptools,development
Classifier: Development Status :: 3 - Alpha
Classifier: Intended Audience :: Developers
Classifier: Topic :: Software Development :: Build Tools
Classifier: License :: OSI Approved :: MIT License
Classifier: Programming Language :: Python :: 3
Classifier: Programming Language :: Python :: 3.9
Classifier: Programming Language :: Python :: 3.10
Classifier: Programming Language :: Python :: 3.11
Classifier: Programming Language :: Python :: 3.12
Classifier: Programming Language :: Python :: 3.13
Classifier: Programming Language :: Python :: 3 :: Only
Requires-Python: >=3.9
License-File: LICENSE
Provides-Extra: cicd
Requires-Dist: build; extra == "cicd"
Requires-Dist: pytest; extra == "cicd"
Requires-Dist: pytest-cov; extra == "cicd"
Dynamic: license-file
